[{"t":"OUR PRODUCTS | FEATURED BRANDS | ABBOTT U.S.","u":"https://www.abbott.com/product-list.html"},{"t":"ABBOTT LABORATORIES - WIKIPEDIA","u":"https://en.wikipedia.org/wiki/Abbott_Laboratories"},{"t":"AMAZON.CO.UK: ABBOTT LABORATORIES","u":"https://www.amazon.co.uk/abbott-laboratories/s?k=abbott+laboratories"},{"t":"ABBOTT | LIFE-CHANGING HEALTH CARE TECHNOLOGIES","u":"https://www.abbott.com/"},{"t":"WHO WE ARE | ABOUT ABBOTT | ABBOTT U.S.","u":"https://www.abbott.com/about-abbott/who-we-are.html"},{"t":"ABBOTTSTORE | PRODUCTS FOR EVERY STAGE OF LIFE","u":"https://abbottstore.com/"},{"t":"FOR CONSUMERS | CONSUMER PRODUCTS | ABBOTT U.S.","u":"https://www.abbott.com/consumer.html"},{"t":"AMAZON.CA: ABBOTT LABORATORIES: HEALTH & PERSONAL CARE","u":"https://www.amazon.ca/Health-Personal-Care-Abbott-Laboratories/s?rh=n:6205177011,p_4:Abbott+Laboratories"},{"t":"ABBOTT LABORATORIES – PRODUCTS, HISTORY, LAWSUITS AND RECALLS","u":"https://www.drugwatch.com/manufacturers/abbott-laboratories/"},{"t":"NUTRITION | FOR CONSUMERS | ABBOTT U.S.","u":"https://www.abbott.com/consumer/nutrition.html"},{"t":"AMAZON.IN: ABBOTT BRAND STORE: HEALTH & PERSONAL CARE","u":"https://www.amazon.in/b?ie=UTF8&node=11417663031"},{"t":"AMAZON.CA: ABBOTT LABORATORIES","u":"https://www.amazon.ca/abbott-laboratories/s?k=abbott+laboratories"},{"t":"ABBOTT LABORATORIES PRODUCTS - MEDEX SUPPLY","u":"https://medexsupply.com/abbott-laboratories/"},{"t":"ABOUT ABBOTT | LIFE-CHANGING TECHNOLOGY | ABBOTT U.S.","u":"https://www.abbott.com/about-abbott.html"},{"t":"AMAZON.COM: ABBOTT","u":"https://www.amazon.com/abbott/s?k=abbott"},{"t":"HISTORY & HERITAGE | CORE LABORATORY AT ABBOTT","u":"https://www.corelaboratory.abbott/us/en/about-us/history-heritage.html"},{"t":"ABBOTT PRODUCTS | NUTRITION SUPPORT FOR INFANTS, CHILDREN AND ADULTS","u":"https://www.abbottnutrition.com/our-brands"},{"t":"UNDER MAINTENANCE","u":"https://abbottstore.com/index.html"},{"t":"ALL MOLECULAR DIAGNOSTICS PRODUCTS","u":"https://www.molecular.abbott/us/en/offerings/products"},{"t":"ABBOTT LABORATORIES","u":"https://www.r9farmacia.com/brand/388-abbott-laboratories"}]