[{"t":"ERT STORE @ AMAZON.COM:","u":"https://www.amazon.com/s?i=merchant-items&me=A2034A5BB1FRLZ"},{"t":"AMAZON.COM: ERT","u":"https://www.amazon.com/stores/page/1CDEEE0C-84EF-4620-B2B6-B3483871A870"},{"t":"How do Stores work with other Amazon Ads products?","u":"https://advertising.amazon.com/solutions/products/stores"},{"t":"Amazon Brand Registry | Sell on Amazon","u":"https://brandservices.amazon.com/"},{"t":"List of Amazon brands - Wikipedia","u":"https://en.wikipedia.org/wiki/List_of_Amazon_brands"},{"t":"Brand Stores: Create a brand page on Amazon for free | Amazon Ads","u":"https://advertising.amazon.com/solutions/products/stores"},{"t":"Amazon.in: : All Categories","u":"https://www.amazon.in/b?ie=UTF8&node=15390370031"},{"t":"Amazon.com: : All Departments","u":"https://www.amazon.com/b?ie=UTF8&node=17602470011"},{"t":"Amazon - Koto Studio","u":"https://koto.studio/work/amazon/"},{"t":"Amazon brand usage guidelines for 3-party display ads | Amazon Ads","u":"https://advertising.amazon.com/resources/ad-policy/brand-usage"},{"t":"Our Brands @ Amazon.com","u":"https://www.amazon.com/b?ie=UTF8&node=17728530011"},{"t":"Amazon.com: Our Brands: Clothing, Shoes & Jewelry","u":"https://www.amazon.com/b?ie=UTF8&node=16334314011"},{"t":"Amazon Brand Name policy","u":"https://sellercentral.amazon.com/help/hub/reference/external/G2N3GKE5SGSHWYRZ?locale=en-US"},{"t":"Amazon.com: Best of Premium Brands","u":"https://www.amazon.com/b?ie=UTF8&node=24001920011"},{"t":"r/AmazonVine on Reddit: What does \"Amazon Brand\" mean?","u":"https://www.reddit.com/r/AmazonVine/comments/yusyhm/what_does_amazon_brand_mean/"},{"t":"Launch your brand with Amazon.in","u":"https://brandservices.amazon.in/"},{"t":"Amazon Brand Profile","u":"https://brandirectory.com/brands/amazon"},{"t":"Amazon Brand Registry - Cost, Benefits, & Requirements - Jungle Scout","u":"https://www.junglescout.com/blog/amazon-brand-registry/"},{"t":"Top Brands from Amazon.com's Bestseller Rankings: Monthly Report","u":"https://metricscart.com/bestseller-reports/amazon-com/brands/"}]