[{"t":"AMAZON.COM: GPARTSDEN: CABLE","u":"https://www.amazon.com/stores/Gpartsden/Cable/page/93262D81-2542-4D1F-9176-005A7EBDD4CD"},{"t":"GPARTSDEN ON AMAZON.COM MARKETPLACE - SELLERRATINGS.COM","u":"https://www.sellerratings.com/amazon/usa/gpartsden"},{"t":"AMAZON.COM : GPARTSDEN 946-04173E DECK ENGAGEMENT CABLE FITS YARD MACHINES MTD BOLENS YARD MAN REPLACES 946-04173D 746-04173 946-04173C 946-04173B 746-04173B AND 746-04173A : PATIO, LAWN & GARDEN","u":"https://www.amazon.com/946-04173E-Engagement-946-04173D-946-04173C-946-04173B/dp/B084VCD5DS"},{"t":"AMAZON.COM: REPLACEMENT PARTS: AUTOMOTIVE: BODY & TRIM, BRAKE SYSTEM, SHOCKS, STRUTS & SUSPENSION & MORE","u":"https://www.amazon.com/Replacement-Parts-Automotive/b?ie=UTF8&node=15719731"},{"t":"AMAZON.COM: GPARTSDEN 115-5680 AUGER CABLE REPLACEMENT FOR TORO 106-4599 1155680 SNOWBLOWER/SNOW THROWER : PATIO, LAWN & GARDEN","u":"https://www.amazon.com/Gpartsden-115-5680-Auger-Cable-Replacement/dp/B0BDJSBJKL"},{"t":"AUTOMOTIVE PARTS & ACCESSORIES - AMAZON.COM","u":"https://www.amazon.com/automotive-auto-truck-replacements-parts/b?ie=UTF8&node=15684181"},{"t":"GPARTSDEN 26\" SNOW BLOWER SCRAPER BAR REPLACEMENT 790-00121-0637 SHAVE PLATE FOR MTD 2 STAGE SNOW THROWER 784-5579A : AMAZON.CA: PATIO, LAWN & GARDEN","u":"https://www.amazon.ca/Gpartsden-Scraper-Replacement-790-00121-0637-784-5579A/dp/B09L62XHJ9"},{"t":"AMAZON.COM : GPARTSDEN GY21641 GY21287 CONTROL CABLE REPLACEMENT FOR JOHN DEERE D100 D105 D110 D120 D125 LAWN MOWER : PATIO, LAWN & GARDEN","u":"https://www.amazon.com/Gpartsden-GY21641-GY21287-Control-Replacement/dp/B09XQ8RR7J"},{"t":"AMAZON.COM: GPARTSDEN 137644 REPLACEMENT DECK WHEEL BOLTS WITH LOCK NUTS FOR CUB CADET CRAFTSMAN POULAN HUSQVARNA LAWN MOWER DECK WHEEL REPLACES 137644 184219 193406 738-3056 938-3056 73930600 : PATIO, LAWN & GARDEN","u":"https://www.amazon.com/Gpartsden-Replacement-Craftsman-Husqvarna-Replaces/dp/B08XY2HJ1T"},{"t":"AMAZON","u":"https://www.amazon.ca/Gpartsden-585271601-Deflector-Husqvarna-Snowblower/dp/B08GLY422R"},{"t":"GPARTSDEN 754-0343 754-0142 DRIVE BELT 3/8\" X 31\"FOR MTD 754-0343 754-0205 ARIENS 0720990 SNOWBLOWERS : AMAZON.IN: GARDEN & OUTDOORS","u":"https://www.amazon.in/Gpartsden-754-0343-754-0142-754-0205-Snowblowers/dp/B0CJ95SPD5"},{"t":"AMAZON.COM: GPARTSDEN P25 STRING TRIMMER HEAD GRASS TRIMMER HEAD FOR HUSQVARNA 128CD POULAN WEEDEATER PPB150E PPB330 REPLACES 537419214 537419205 : PATIO, LAWN & GARDEN","u":"https://www.amazon.com/Gpartsden-Husqvarna-Weedeater-537419214-537419205/dp/B08XY58N12"},{"t":"AMAZON.COM : GPARTSDEN 99-1510 TRACTION CONTROL CABLE FOR TORO 20022 20023 20023C 20025 20027 20029 20035 20652 20653 20061 LAWN MOWER : PATIO, LAWN & GARDEN","u":"https://www.amazon.com/Gpartsden-99-1510-Traction-Control-20023C/dp/B09C6C98DB"},{"t":"AMAZON.COM : GPARTSDEN 189182 MOWER SELF PROPELLED DRIVE CABLE 532189182 FOR CRAFTSMAN HUSQVARNA 60-104 LAWN TRACTOR PARTS : PATIO, LAWN & GARDEN","u":"https://www.amazon.com/Gpartsden-Propelled-532189182-Craftsman-Husqvarna/dp/B09VKTMC85"},{"t":"AMAZON.COM: GPARTSDEN 196103 MOWER DECK DRIVE BELT 54\" FITS HUSQVARNA SEARS CRAFTSMAN JONSERED REPLACES 196103 532196103 147-1/2\"X5/8\" : PATIO, LAWN & GARDEN","u":"https://www.amazon.com/Gpartsden-Husqvarna-Craftsman-Jonsered-532196103/dp/B08597TP9P"},{"t":"AMAZON.COM : GPARTSDEN 532447570 DRIVE CONTROL CABLE FOR CRAFTSMAN HUSQVARNA 532447570 LAWN MOWER CABLE : PATIO, LAWN & GARDEN","u":"https://www.amazon.com/Gpartsden-532447570-Control-Craftsman-Husqvarna/dp/B0CWK8SPH1"},{"t":"GPARTSDEN GX23805 DRIVE CABLE FOR JOHN DEERE JS36 JS46 JM36 JM46 JS38 JS48 WALK BEHIND MOWER : AMAZON.CO.UK: GARDEN","u":"https://www.amazon.co.uk/Gpartsden-GX23805-Drive-Cable-Behind/dp/B099KD6F74"},{"t":"AMAZON.COM : GPARTSDEN 107-0799 BLADE BRAKE CABLE FOR TORO 20047 20068 20075 20076 20076A 20658 LAWN MOWER : PATIO, LAWN & GARDEN","u":"https://www.amazon.com/Gpartsden-107-0799-Blade-Brake-20076A/dp/B097K2CGCR"},{"t":"AMAZON.COM : GPARTSDEN 105-1845 290-931 TRACTION CONTROL CABLE FOR TORO 22\" SELF PROPELLED FRONT DRIVE RECYCLER LAWN MOWER : PATIO, LAWN & GARDEN","u":"https://www.amazon.com/Gpartsden-105-1845-Traction-Control-Length/dp/B084VBR9KW"},{"t":"AMAZON.COM: GPARTSDEN SET OF 2 954-0430 754-0430 AUGER COGGED V BELT REPLACEMENT FOR MTD TROY BILT CUB CADET 954-0430A 754-0430A SNOW THROWER : PATIO, LAWN & GARDEN","u":"https://www.amazon.com/Gpartsden-954-0430A-SnowBlower-Replaces-754-0430A/dp/B08GM36Y6J"}]