[{"t":"INNOPLAST, INC. @ AMAZON.COM:","u":"https://www.amazon.com/s?i=merchant-items&me=ACVRQFM05269I"},{"t":"AMAZON.COM: INNOPLAST","u":"https://www.amazon.com/stores/Innoplast/Homepage/page/BD2C7110-5114-4036-92E9-0FD8EA26BD69"},{"t":"Innoplast Products - EnSafeCo.com","u":"https://www.ensafeco.com/brands/Innoplast.html"},{"t":"BollardGard 7\" x 52\" 2-Pack Bollard Cover - Innoplast (Black White Tape): Amazon.com: Industrial & Scientific","u":"https://www.amazon.com/BollardGard-Bollard-Cover-Packs-Innoplast/dp/B0BWFTB34V"},{"t":"Amazon.com: Innoplast - ClearanceGard 4 In x 80 In Clearance Bar Kit- Clearance X In - XX In Lettering - Innoplast (Yellow Red Tape) : Automotive","u":"https://www.amazon.com/80-Yellow-Clearance-Bar-Kit/dp/B07T6JTL8C"},{"t":"Innoplast 4\" x 52\" (4.7\" ID) Bollard Cover Yellow with No Reflective: Amazon.com: Industrial & Scientific","u":"https://www.amazon.com/Innoplast-Bollard-Cover-Yellow-Reflective/dp/B00MQ5V33K"},{"t":"BollardGard 7\" x 52\" Bollard Cover Red - Innoplast (Red Black Tape): Amazon.com: Tools & Home Improvement","u":"https://www.amazon.com/BollardGard-Bollard-Cover-Red-Innoplast/dp/B09Z3B1B3J"},{"t":"Innoplast BollardGard 4\" x 52\" 1-Pack Round Top Bollard Cover (Black No Tape): Amazon.com: Industrial & Scientific","u":"https://www.amazon.com/BollardGard-Round-Bollard-Cover-Packs/dp/B0BWBWJTLF"},{"t":"Bollardgard 4\" x 52\" Bollard Cover Yellow with White Tape - Innoplast: Amazon.com: Industrial & Scientific","u":"https://www.amazon.com/Innoplast-Bollardgard-Yellow-White-4-700/dp/B00MQ5V1IC"},{"t":"Amazon.com: BollardGard 7\" x 52\" Bollard Cover Yellow - Innoplast ...","u":"https://www.amazon.com/Innoplast-BollardGard-Bollard-Yellow-Reflective/dp/B01J27SH6A"},{"t":"Amazon.com: Innoplast BollardGard 7\" x 52\" Bollard Cover Blue (Blue Yellow Tape) : Tools & Home Improvement","u":"https://www.amazon.com/BollardGard-Bollard-Cover-Blue-Innoplast/dp/B09Z4MLQBL"},{"t":"Amazon.com. Spend less. Smile more.","u":"https://www.amazon.com/s?me=ACVRQFM05269I"},{"t":"Amazon.com: Innoplast 8\" x 72\" (9.125\" ID) Bollard Cover Yellow with No Reflective : Industrial & Scientific","u":"https://www.amazon.com/Innoplast-Bollard-Cover-Yellow-Reflective/dp/B006LP2718"},{"t":"Innoplast | one of EnSafeCo's premier brands","u":"https://www.ensafeco.com/innoplast/"},{"t":"BollardGard 4\" x 64\" 1-Pack Round Top Bollard Cover - Innoplast (Red No Tape): Amazon.com: Industrial & Scientific","u":"https://www.amazon.com/BollardGard-Round-Bollard-Cover-Packs/dp/B0BWPM3VY7"},{"t":"Amazon.com: Innoplast: Column Protection","u":"https://www.amazon.com/stores/Innoplast/ColumnProtection/page/7561344B-31AA-4740-8BDF-89A4AC93EC2E"},{"t":"Amazon.com: ClearanceGard 4″ x 96″ Clearance Bar Kit- Clearance ...","u":"https://www.amazon.com/ClearanceGard-Clearance-Bar-Yellow-Tape/dp/B09XFFM9XC"},{"t":"Innoplast BollardGard 7\" x 60\" 1-Pack Round Top Bollard Cover (Black no Tape): Amazon.com: Industrial & Scientific","u":"https://www.amazon.com/BollardGard-Round-Bollard-Cover-Packs/dp/B0BWSGMZP1"},{"t":"BollardGard 4\" x 52\" Bollard Cover - Innoplast (Black Green Tape): ...","u":"https://www.amazon.com/Innoplast-Bollardgard-Black-White-4-700/dp/B01EIN4S6G"},{"t":"Soft Padded Bollard Cover 7\" x 50\" - Innoplast (Black white tape) - Amazon.com","u":"https://www.amazon.com/Soft-Padded-Bollard-Cover-Innoplast/dp/B0B445VQTP"}]