[{"t":"AMAZON.COM","u":"https://www.amazon.com/s?me=AMZUCGNLENC41"},{"t":"AMAZON.COM: JARSANT EASTER BUNNY CARROT HOUSE BUILDING SET, 2 RABBITS, CHICK, COLORFUL EASTER EGG AND BASKET TOY, BRICKHEADZ PETS BUILDING BLOCKS KIT GIFT FOR BOYS GIRLS TODDLERS : TOYS & GAMES","u":"https://www.amazon.com/Jarsant-Building-Colorful-Brickheadz-Toddlers/dp/B0CNMZZ8YZ"},{"t":"JARSANT 230FT WIRELESS REMOTE DIGITAL BARBECUE THERMOMETER PROBE FOR SALE ONLINE | EBAY","u":"https://www.ebay.com.au/p/27026930729"},{"t":"AMAZON.IN: : ALL CATEGORIES","u":"https://www.amazon.in/b?ie=UTF8&node=15390370031"},{"t":"AMAZON.COM: MASON JARS","u":"https://www.amazon.com/mason-jars/s?k=mason+jars"},{"t":"AMAZON.COM: JARS","u":"https://www.amazon.com/jars/s?k=jars"},{"t":"JARSON @ AMAZON.COM:","u":"https://www.amazon.com/s?i=merchant-items&me=AXRFRPI08GXNV"},{"t":"AMAZON.COM: CAR GUARDIANCE 1 T5 20W 6PCS, LED SHOP LIGHT 4FT 20W-537 ...","u":"https://www.amazon.com/Jarsant-Integrated-Fixture-Utility-Electric/dp/B071K3Z5NB"},{"t":"AMAZON.COM: CUSTOMER REVIEWS: CAR GUARDIANCE 1 T5 20W 6PCS, LED SHOP LIGHT 4FT 20W-537","u":"https://www.amazon.com/Jarsant-Integrated-Fixture-Utility-Electric/product-reviews/B071K3Z5NB"},{"t":"AMAZON.IN: VASTRANAND","u":"https://www.amazon.in/stores/VASTRANAND/page/5239FBAA-9092-4423-9696-43BB2AC4A6CA"},{"t":"AMAZON BRAND REGISTRY | SELL ON AMAZON","u":"https://sell.amazon.com/brand-registry"},{"t":"AMAZON.COM: OUR BRANDS: CLOTHING, SHOES & JEWELRY","u":"https://www.amazon.com/b?ie=UTF8&node=16334314011"},{"t":"AMAZON.COM: JORDAN BRAND","u":"https://www.amazon.com/jordan-brand/s?k=jordan+brand"},{"t":"AMAZON - KOTO STUDIO","u":"https://koto.studio/work/amazon/"},{"t":"OUR BRANDS","u":"https://www.amazon.com/fmc/m/20190596?almBrandId=QW1hem9uIEZyZXNo"},{"t":"AMAZON.COM: : ALL DEPARTMENTS","u":"https://www.amazon.com/b?ie=UTF8&node=17602470011"},{"t":"LIST OF AMAZON BRANDS - WIKIPEDIA","u":"https://en.wikipedia.org/wiki/List_of_Amazon_brands"},{"t":"AMAZON.COM: JAR","u":"https://www.amazon.com/jar/s?k=jar"},{"t":"ABOUT US | ABOUT AMAZON","u":"https://www.aboutamazon.com/about-us"}]