[{"t":"AMAZON.COM: PBS MASTERPIECE - PRIME VIDEO / PRIME VIDEO: MOVIES & TV","u":"https://www.amazon.com/PBS-Masterpiece-Prime-Video/s?rh=n%3A169174011%2Cp_n_subscription_id%3A16709388011"},{"t":"AMAZON.COM: THE 99 MOST ESSENTIAL TCHAIKOVSKY MASTERPIECES (AMAZON EXCLUSIVE) : VARIOUS ARTISTS: DIGITAL MUSIC","u":"https://www.amazon.com/Essential-Tchaikovsky-Masterpieces-Amazon-Exclusive/dp/B002S3AI18"},{"t":"AMAZON.COM: PBS MASTERPIECE - PRIME VIDEO: MOVIES & TV","u":"https://www.amazon.com/Prime-Video-PBS-Masterpiece-Movies-TV/s?rh=n:2858778011,p_n_subscription_id:16709388011"},{"t":"PLAY THE 99 MOST ESSENTIAL MOZART MASTERPIECES BY VARIOUS ARTISTS ON AMAZON MUSIC","u":"https://www.amazon.com/99-Most-Essential-Mozart-Masterpieces/dp/B001NJUGV0"},{"t":"PBS MASTERPIECE","u":"https://www.amazon.com/gp/video/offers?benefitId=masterpiece"},{"t":"PBS MASTERPIECE AMAZON CHANNEL - FULL LIST OF MOVIES AND TV SHOWS ONLINE","u":"https://www.justwatch.com/us/provider/pbs-masterpiece-amazon-channel"},{"t":"AMAZON.COM: MASTERPIECE THEATRE: MOVIES & TV","u":"https://www.amazon.com/Masterpiece-Theatre-Movies-TV/s?k=Masterpiece+Theatre&rh=n:2625373011"},{"t":"AMAZON.COM: MASTERPIECE - PRIME VIDEO: MOVIES & TV","u":"https://www.amazon.com/masterpiece-Prime-Video-Movies-TV/s?k=masterpiece&rh=n:2858778011"},{"t":"WATCH MASTERPIECES | PRIME VIDEO","u":"https://www.amazon.com/Masterpieces-Christopher-Alles/dp/B07YZRHC9H"},{"t":"AMAZON.COM: MASTERPIECES","u":"https://www.amazon.com/stores/MasterPieces/page/6FFD7CF1-3646-4711-A01A-4ECD04EE4BC5"},{"t":"AMAZON BEST SELLERS: BEST OUR BRANDS","u":"https://www.amazon.com/Best-Sellers-Our-Brands/zgbs/private-brands"},{"t":"AMAZON.COM: PRIME VIDEO: PRIME VIDEO","u":"https://www.amazon.com/masterpiece"},{"t":"WATCH PBS MASTERPIECE ON PRIME VIDEO","u":"https://www.amazon.com/gp/video/storefront/subscription/masterpiece"},{"t":"AMAZON.COM: PBS MASTERPIECE - PRIME TV SHOWS / PRIME VIDEO: MOVIES & TV","u":"https://www.amazon.com/Prime-TV-Shows-PBS-Masterpiece-Video/s?rh=n:2864549011,p_n_subscription_id:16709388011"},{"t":"AMAZON.COM: PBS MASTERPIECE - PRIME MOVIES / PRIME VIDEO: MOVIES & TV","u":"https://www.amazon.com/Movies-PBS-Masterpiece-Prime-Video/s?rh=n%3A2858905011%2Cp_n_subscription_id%3A16709388011"}]