[{"t":"AMAZON.COM: QUALITY MASCOTS COSTUMES: CLOTHING, SHOES & JEWELRY","u":"https://www.amazon.com/Clothing-Shoes-Jewelry-QUALITY-MASCOTS-COSTUMES/s?rh=n:7141123011,p_4:QUALITY+MASCOTS+COSTUMES"},{"t":"AMAZON.COM: MASCOT COSTUMES","u":"https://www.amazon.com/Mascot-Costumes/s?k=Mascot+Costumes"},{"t":"AMAZON.COM: MASCOT WORKWEAR: CLOTHING, SHOES & JEWELRY","u":"https://www.amazon.com/Clothing-Shoes-Jewelry-Mascot-Workwear/s?rh=n:7141123011,p_4:Mascot%2BWorkwear"},{"t":"AMAZON.COM: MASCOT","u":"https://www.amazon.com/stores/MASCOT/Homepage/page/82636032-D7B3-4782-B694-09EDD8CB0165"},{"t":"AMAZON.COM: DRESS UP AMERICA: MASCOTS","u":"https://www.amazon.com/stores/DressUpAmerica/Mascots/page/FC5E4A3E-6D73-41A4-AA24-B49F1F22B270"},{"t":"AMAZON.COM: MASCOT COSTUME","u":"https://www.amazon.com/Mascot-Costume/s?k=Mascot+Costume"},{"t":"AMAZON.COM: CARTOON MASCOT COSTUME","u":"https://www.amazon.com/Cartoon-Mascot-Costume/s?k=Cartoon+Mascot+Costume"},{"t":"AMAZON.COM: CHEERLEADING MASCOT COSTUMES - CHEERLEADING MASCOT COSTUMES / CHEERLEADING EQUIP...: SPORTS & OUTDOORS","u":"https://www.amazon.com/Cheerleading-Mascot-Costumes/b?ie=UTF8&node=3402211"},{"t":"AMAZON.COM:","u":"https://www.amazon.com/s?i=merchant-items&me=A3MGZ5C1Z186BY"},{"t":"MEET PECCY, THE BIZARRE, BELOVED MASCOT YOU DIDN’T KNOW AMAZON HAD","u":"https://www.fastcompany.com/90329525/amazon-peccy"},{"t":"AMAZON.IN: MASCOT - MEN'S CLOTHING: CLOTHING & ACCESSORIES","u":"https://amazon.in/Men-MASCOT-Clothing-Accessories/s?rh=n%3A1968024031%2Cp_89%3AMASCOT"},{"t":"MASCOT WORKWEAR AND SAFETY FOOTWEAR - TESTED TO WORK","u":"https://www.mascotworkwear.com/en/"},{"t":"R/AMAZONFC ON REDDIT: I'VE ALWAYS WONDERED WHAT OTHER AMAZON MASCOTS THERE ARE.","u":"https://www.reddit.com/r/AmazonFC/comments/189de4s/ive_always_wondered_what_other_amazon_mascots/"},{"t":"MASCOT WORKWEAR","u":"https://www.maworkwear.com"},{"t":"AMAZON.COM: MASCOT WORKWEAR","u":"https://www.amazon.com/mascot-workwear/s?k=mascot+workwear"},{"t":"MASCOT WORKWEAR & SAFETY FOOTWEAR | FULL COLLECTION | LOWEST PRICES AT TUFFSHOP","u":"https://tuffshop.co.uk/search-by-brand/mascot-workwear.html"},{"t":"MASCOT COSTUMES AND ACCESSORIES - BOOSTERS INCORPORATED","u":"https://boostersinc.net/collections/mascots"},{"t":"MASCOTS - DRESS UP AMERICA","u":"https://dressupamerica.com/collections/mascots"}]