[{"t":"SMILE (BANK) - WIKIPEDIA","u":"https://en.m.wikipedia.org/wiki/Smile_(bank)"},{"t":"AMAZON.COM: SMILE.AMAZON","u":"https://www.amazon.com/smile-amazon/s?k=smile.amazon"},{"t":"AMAZON SG BANKS ON SMILE LOGO TO BUILD BRAND AFFINITY IN OOH AND DIGITAL CAMPAIGN | MARKETING-INTERACTIVE","u":"https://www.marketing-interactive.com/amazon-sg-banks-on-smile-logo-to-build-brand-affinity-in-ooh-and-digital-campaign"},{"t":"AMAZON.COM. SPEND LESS. SMILE MORE.","u":"https://smile.amazon.com/"},{"t":"AMAZON.COM: SMILE ACCOUNT","u":"https://www.amazon.com/smile-account/s?k=smile+account"},{"t":"AMAZON.CO.UK: SMILE.AMAZON","u":"https://www.amazon.co.uk/smile-amazon/s?k=smile.amazon"},{"t":"AMAZON.COM: AMAZON.SMILE.COM","u":"https://www.amazon.com/amazon-smile-com/s?k=amazon.smile.com"},{"t":"AMAZON CLOSING AMAZONSMILE TO FOCUS ITS PHILANTHROPIC GIVING TO PROGRAMS WITH GREATER IMPACT","u":"https://www.aboutamazon.com/news/company-news/amazon-closing-amazonsmile-to-focus-its-philanthropic-giving-to-programs-with-greater-impact"},{"t":"AMAZON SMILE","u":"https://www.ageuk.org.uk/hounslow/get-involved/donate/amazon-smile2/"},{"t":"AMAZON BRAND USAGE GUIDELINES FOR 3-PARTY DISPLAY ADS | AMAZON ADS","u":"https://advertising.amazon.com/resources/ad-policy/brand-usage"},{"t":"AMAZON SMILE | BRANDS OF THE WORLD™ | DOWNLOAD VECTOR LOGOS AND LOGOTYPES","u":"https://www.brandsoftheworld.com/logo/amazon-smile"},{"t":"GIVE WITH AMAZON SMILE — SAN DIEGO BLOOD BANK FOUNDATION","u":"https://sdbbfoundation.org/smile-amazon-give"},{"t":"ABOUT: SMILE (BANK)","u":"https://dbpedia.org/page/Smile_(bank)"},{"t":"AMAZON.COM: AMAZON.SMILE.COM SIGN IN","u":"https://www.amazon.com/amazon-smile-com-sign/s?k=amazon.smile.com+sign+in"},{"t":"HOW TO SET UP AMAZON SMILE FOR YOUR NONPROFIT — TECHNOLOGY ALOHA","u":"https://technologyaloha.com/how-to-set-up-an-amazon-smile-account-for-your-nonprofit/"},{"t":"AMAZON LOGO AND SYMBOL, MEANING, HISTORY, PNG, BRAND","u":"https://1000logos.net/amazon-logo/"},{"t":"AMAZONSMILE ORG CENTRAL: CUSTOMERS SHOP. AMAZON GIVES.","u":"https://org.amazon.com/"},{"t":"SUPPORT WITH AMAZONSMILE | THE FOOD BANK OF WESTERN MASSACHUSETTS","u":"https://www.foodbankwma.org/events/amazonsmile/"},{"t":"FUNDRAISING FOR CAMPS | AMERICAN CAMP ASSOCIATION","u":"https://www.acacamps.org/resource-library/fundraising/how-register-receive-donations-through-amazonsmile"},{"t":"AMAZON SMILE – COMMUNITY HARVEST FOOD BANK","u":"https://www.communityharvest.org/give-help/amazon-smile/"}]