[{"t":"TOPEAK STORE @ AMAZON.COM:","u":"https://www.amazon.com/s?i=merchant-items&me=AE6XPWP5XZG6W"},{"t":"AMAZON.COM: TOPEAK","u":"https://www.amazon.com/stores/Topeak/page/6FAFD573-3277-4268-B7C2-C7BA4BEC78A1"},{"t":"BRANDS CYCLE AND FITNESS @ AMAZON.COM: TOPEAK","u":"https://www.amazon.com/s?i=merchant-items&me=A3CFE8KIJUOW5H&rh=p_4:Topeak"},{"t":"TOPEAK - PREPARE TO RIDE | TOPEAK","u":"https://www.topeak.com/us/en"},{"t":"AMAZON.COM: TOPEAK: BAGS","u":"https://www.amazon.com/stores/Topeak/Bags/page/1605DB94-7BFB-42DD-B981-9A972F3CAEEE"},{"t":"AMAZON.COM: TOPEAK: RACKS","u":"https://www.amazon.com/stores/page/14BC1553-8D34-4B4A-89A5-7920E6C767C6"},{"t":"TOPEAK TOP 20 PRODUCTS FROM CYCLING EQUIPMENT BRAND - FINDTHISBEST","u":"https://www.findthisbest.com/brand/116-topeak"},{"t":"AMAZON.COM: BIKE RACKS - TOPEAK / BIKE RACKS & BAGS / CYCLING EQUIPMENT: SPORTS & OUTDOORS","u":"https://www.amazon.com/Bike-Racks-Bags-Topeak-Cycling-Equipment/s?keywords=Bike+Racks&rh=n:6389515011,p_89:Topeak&c=ts&ts_id=6389515011"},{"t":"AMAZON.COM: TOPEAK: TOOLS","u":"https://www.amazon.com/stores/Topeak/page/C73B393F-6DAC-4A3C-BF5A-9AA309D5F223"},{"t":"AMAZON.COM : TOPEAK MTX TRUNK BAG DXP BICYCLE TRUNK BAG WITH RIGID MOLDED PANELS : SPORTS & OUTDOORS","u":"https://www.amazon.com/Topeak-Trunk-Bicycle-Molded-Panels/dp/B01LW3W2Z8"},{"t":"AMAZON.CA: TOPEAK","u":"https://www.amazon.ca/topeak/s?k=topeak"},{"t":"AMAZON.COM: BIKE BASKETS - TOPEAK / BIKE BASKETS / BIKE RACKS & BAGS: SPORTS & OUTDOORS","u":"https://www.amazon.com/Bike-Baskets-Topeak-Racks-Bags/s?keywords=Bike+Baskets&rh=n:194528011,p_89:Topeak&c=ts&ts_id=194528011"},{"t":"AMAZON.COM: TOPEAK RACK","u":"https://www.amazon.com/topeak-rack/s?k=topeak+rack"},{"t":"AMAZON.CA: TOPEAK: SPORTS & OUTDOORS","u":"https://www.amazon.ca/Sports-Outdoors-Topeak/s?rh=n:2242989011,p_89:Topeak"},{"t":"AMAZON.COM : TOPEAK EXPLORER RACK : SPORTS & OUTDOORS","u":"https://www.amazon.com/Topeak-62431-Explorer-Rack/dp/B08B1WTFS5"},{"t":"AMAZON.CA: TOPEAK - CYCLING EQUIPMENT: SPORTS & OUTDOORS","u":"https://www.amazon.ca/Cycling-Equipment-Topeak-Sports-Outdoors/s?rh=n:2406106011,p_89:Topeak"},{"t":"AMAZON.IN: TOPEAK - CYCLING RACKS / CYCLING ACCESSORIES: SPORTS, FITNESS & OUTDOORS","u":"https://www.amazon.in/Cycling-Racks-Topeak-Accessories/s?rh=n:3404533031,p_89:Topeak"},{"t":"TOPEAK : AMAZON.ES: DEPORTES Y AIRE LIBRE","u":"https://www.amazon.es/Topeak-TC1016/dp/B004BU6ZAY"}]