[{"t":"AMAZON.COM: TREND ENTERPRISES, INC.","u":"https://www.amazon.com/stores/TRENDenterprisesInc/Homepage/page/8D7E9417-1F39-4AE1-9F63-A25F2D8A9DD4"},{"t":"Amazon.com: TREND enterprises, Inc.: What's New","u":"https://www.amazon.com/stores/TRENDenterprisesInc/WhatsNew/page/7D88887F-24AC-4E25-8630-99C935FFF91B"},{"t":"Apply to sell a product, category, or brand in the Amazon store","u":"https://www.youtube.com/watch?v=9jHjIV2DBds"},{"t":"Amazon Private Brands - YouTube","u":"https://www.youtube.com/watch?v=3UJ9cMsxVyA"},{"t":"Amazon.co.uk: TREND ENTERPRISES INC.","u":"https://www.amazon.co.uk/TREND-ENTERPRISES-INC/s?k=TREND+ENTERPRISES+INC."},{"t":"Amazon.com: TREND enterprises, Inc.: Best Sellers","u":"https://www.amazon.com/stores/page/6248B30B-F4D8-4FBA-A63F-A39DF05608CF"},{"t":"TREND Enterprises - Shop by Brand | Maisonette","u":"https://www.maisonette.com/brands/trend-enterprises"},{"t":"TREND ENTERPRISES INC. T-38163 CHART SYNONYMS GRADES 3-6 : Amazon.co.uk: Toys & Games","u":"https://www.amazon.co.uk/TREND-ENTERPRISES-INC-T-38163-SYNONYMS/dp/B000NX12KQ"},{"t":"Amazon","u":"https://www.amazon.com/TREND-enterprises-Order-Operations-Learning/dp/B000Q7CNIE"},{"t":"Trend Enterprises Inc Teaching & Classroom Supplies","u":"https://www.walmart.com/c/brand/trend-enterprises-inc-teaching-classroom-supplies"},{"t":"TREND enterprises, Inc. Educational Classroom Supplies","u":"https://www.trendenterprises.com/"},{"t":"TREND enterprises, Inc. Silver Metallic Terrific Trimmers, 32.5 ft : Amazon.co.uk: Stationery & Office Supplies","u":"https://www.amazon.co.uk/Enterprises-Silver-Metallic-Terrific-Trimmers/dp/B000F8QVSC"},{"t":"Amazon.com: TREND ENTERPRISES, INC. ¡Fabuloso! (SP) Applause Stickers, 100 ct. : Toys & Games","u":"https://www.amazon.com/Trend-Enterprises-%C2%A1Fabuloso-Applause-Stickers/dp/B000NNO2TE"},{"t":"TREND enterprises, Inc. Our Hundreds Chart Learning Chart, 17\" x 22\" : Amazon.in: Office Products","u":"https://www.amazon.in/Trend-Enterprises-Hundreds-Learning-T-38275/dp/B001JTJGF6"},{"t":"Trend Enterprises : Target","u":"https://www.target.com/b/trend-enterprises/-/N-9s1j9"},{"t":"Amazon.com: TREND enterprises, Inc. Preschool Diploma, 30 ct : Office Products","u":"https://www.amazon.com/TREND-enterprises-Inc-Preschool-Diploma/dp/B000KIEHTW"},{"t":"Amazon.com: TREND Enterprises Stickers","u":"https://www.amazon.com/TREND-enterprises-Stickers/s?k=TREND+enterprises+Stickers"},{"t":"Amazon.com:","u":"https://www.amazon.com/stores/TrendEnterprisesInc/node/11263407011"},{"t":"Products — TREND enterprises, Inc.","u":"https://www.trendenterprises.com/collections/all"},{"t":"The Expert In Anything Was Once A Beginner Banner by TREND ENTERPRISES INC. : Amazon.co.uk: Stationery & Office Supplies","u":"https://www.amazon.co.uk/Anything-Beginner-TREND-ENTERPRISES-INC/dp/B00JFKOKK2"},{"t":"Amazon.com: TREND enterprises, Inc.: Flash Cards","u":"https://www.amazon.com/stores/TRENDenterprisesInc/FlashCards/page/915134C7-A70F-46A4-86F3-660BD77AE6DA"},{"t":"Amazon (company) - Wikipedia","u":"https://en.wikipedia.org/wiki/Amazon_(company)"}]