[{"t":"AMAZON.COM: TURBRO","u":"https://www.amazon.com/stores/TURBRO/TURBRO/page/DBC162A1-B815-4DF2-BF1C-E81E4C53C7B0"},{"t":"AMAZON.COM: TURBRO - ELECTRIC FIREPLACES / FIREPLACES: HOME & KITCHEN","u":"https://www.amazon.com/Electric-Fireplaces-TURBRO/s?rh=n:17160393011,p_89:TURBRO"},{"t":"WHAT RESULTS CAN I EXPECT FROM MY BRAND STORE?","u":"https://advertising.amazon.com/solutions/products/stores"},{"t":"TURBRO - ELECTRIC FIREPLACES, AIR CONDITIONERS, HVAC ACCESSORIES","u":"https://www.turbro.com/"},{"t":"AMAZON.COM: TURBRO: FIREPLACE STOVES","u":"https://www.amazon.com/stores/TURBRO/FireplaceStoves_Heater/page/09B4E41E-BEAE-457E-ACCB-B5451B22B5C5"},{"t":"BRAND STORES: CREATE A BRAND PAGE ON AMAZON FOR FREE | AMAZON ADS","u":"https://advertising.amazon.com/solutions/products/stores"},{"t":"TURBRO STORE","u":"https://www.facebook.com/turbrostore/"},{"t":"AMAZON BRAND REGISTRY | SELL ON AMAZON","u":"https://sell.amazon.com/brand-registry"},{"t":"AMAZON.COM: TURBRO - VACUUM CLEANERS & FLOOR CARE: HOME & KITCHEN","u":"https://www.amazon.com/Vacuum-Cleaners-Floor-Care-TURBRO/s?rh=n:510106,p_89:TURBRO"},{"t":"TURBRO THE BEST AMAZON PRICE IN SAVEMONEY.ES","u":"https://savemoney.es/usa/asin/turbro"},{"t":"TURBRO - THE HOME DEPOT","u":"https://www.homedepot.com/b/TURBRO/N-5yc1vZo7x"},{"t":"AMAZON.COM: : ALL DEPARTMENTS","u":"https://www.amazon.com/amazon-storefront-start/b?ie=UTF8&node=53641474011"},{"t":"SHOP THE BRAND: TURBRO","u":"https://www.wayfair.com/brand/bnd/turbro-b48985.html"},{"t":"TURBRO","u":"https://www.walmart.com/c/brand/turbro"},{"t":"TURBRO | WALMART CANADA","u":"https://www.walmart.ca/en/c/brand/turbro"},{"t":"AMAZON.COM: TURBRO: PORTABLE AIR CONDITIONER","u":"https://www.amazon.com/stores/TURBRO/page/609D9364-7B36-4D57-AA25-DBDC599B96D3"},{"t":"FAIRE","u":"https://www.faire.com/brand/b_ear422mh48"},{"t":"TURBRO REVIEWS | READ CUSTOMER SERVICE REVIEWS OF TURBRO.COM","u":"https://www.trustpilot.com/review/turbro.com"},{"t":"AMAZON.COM : TURBRO 29 INCH SMOKELESS FIRE PIT FOR OUTDOOR WOOD BURNING, STAINLESS STEEL CAMPING STOVE WITH STAND, REMOVABLE ASH PAN, WATERPROOF STORAGE BAG, PLUTO R29, BLACK : PATIO, LAWN & GARDEN","u":"https://www.amazon.com/TURBRO-Inch-Smokeless-Fire-Pit/dp/B0D97D7BJC"}]