[{"t":"AIDELIFE @ AMAZON.CO.UK:","u":"https://www.amazon.co.uk/s?i=merchant-items&me=A3MB5LIMSQ21SA"},{"t":"AIDELIFE TOP 11 PRODUCTS FROM POWER TOOLS BRAND - FINDTHISBEST","u":"https://www.findthisbest.com/brand/267881-aidelife"},{"t":"BECOME A AIDELIFE INFLUENCER AT UBUY!","u":"https://www.u-buy.co.uk/brand/aidelife"},{"t":"COMPARE PRICES FOR AIDELIFE ACROSS ALL EUROPEAN AMAZON STORES","u":"https://www.hagglezon.com/fr/s/Aidelife"},{"t":"AIDELIFE DRILLING DUST COLLECTION ATTACHMENT,UNIVERSAL DUST SHROUD FOR DRILLING AD-1805 : AMAZON.CO.UK: DIY & TOOLS","u":"https://www.amazon.co.uk/Aidelife-Collection-Attachment-Universal-Drilling/dp/B07YQSJ75H"},{"t":"AIDELIFE DUST COLLECTING GUARD,CUTTING DUST SHROUD FOR ANGLE GRINDERS 4-1/2 INCH TO 5 INCH - AMAZON.COM","u":"https://www.amazon.com/Aidelife-collecting-Cutting-Shroud-Grinders/dp/B07YDFR9DN"},{"t":"BUY AIDELIFE PRODUCTS ONLINE AT BEST PRICES IN UK | UBUY","u":"https://www.u-buy.co.uk/brand/aidelife"},{"t":"AIDELIFE EXTERIOR RENOVATOR ACCESSORIES FOR ANGLE GRINDER ...","u":"https://www.amazon.com.be/-/en/Aidelife-Exterior-Renovator-Accessories-Synthetic/dp/B0BT91D7HJ"},{"t":"AMAZON.IN: : ALL CATEGORIES","u":"https://www.amazon.in/b?ie=UTF8&node=15390370031"},{"t":"AIDELIFE SYNTHETIC FIBRE ABRASIVE BRUSH DRUM FOR GRINDING MACHINE RENOVATOR,FOR FLAT METAL AND WOOD SURFACES AND FOR SATIN FINISHING OF UNPAINTED METALS Ø120X100, WIRE DRAWING MACHINE ATTACHMENT : AMAZON.CO.UK: DIY & TOOLS","u":"https://www.amazon.co.uk/Aidelife/dp/B0BT92L7YX"},{"t":"AIDELIFE TOP 15 PRODUCTS FROM ANGLE GRINDERS BRAND - FINDTHISBEST (UK)","u":"https://www.findthisbest.co.uk/brand/30266-aidelife"},{"t":"BUY AIDELIFE PRODUCTS ONLINE AT BEST PRICES IN NEPAL | UBUY","u":"https://www.nepal.ubuy.com/en/brand/aidelife"},{"t":"AMAZON.CO.UK","u":"https://www.amazon.co.uk/Aidelife-Grinder-Collection-Attachment-Double-Cut/dp/B07TKBRZPZ"},{"t":"BRAND-AIDES @ AMAZON.COM: BRAND-AIDES","u":"https://www.amazon.com/s?i=merchant-items&me=A2XTTI8MGJUBS8&rh=p_4:Brand-Aides"},{"t":"AMAZON.COM: : ALL DEPARTMENTS","u":"https://www.amazon.com/b?ie=UTF8&node=17602470011"},{"t":"AMAZON BRAND REGISTRY | SELL ON AMAZON","u":"https://sell.amazon.com/brand-registry"},{"t":"AMAZON.COM: AIDELIFE WOOD BISCUIT PLATE JOINER KIT ACCESSORIES WITH 1X4\" BLADE,ADJUSTABLE ANGLE AND DUST BAG : HOME & KITCHEN","u":"https://www.amazon.com/Aidelife-Biscuit-Joiner-Accessories-Adjustable/dp/B08D3CY5GS"},{"t":"AMAZON - KOTO STUDIO","u":"https://koto.studio/work/amazon/"},{"t":"AMAZON.COM. SPEND LESS. SMILE MORE.","u":"https://www.amazon.com/"},{"t":"AMAZON LIVE - AIDELIFE METAL SHEARS ATTACHMENT","u":"https://www.amazon.com/live/video/01b0edc0301048a2863cea4b326af089?ref_=dp_vse_rvc_9"}]