[{"t":"ALL PRODUCTS","u":"https://arcabrasives.com/products"},{"t":"ARC ABRASIVES ABRASIVES & ABRASIVE PRODUCTS","u":"https://www.grainger.com/category/abrasives?brandName=ARC+ABRASIVES&filters=brandName"},{"t":"ARC ABRASIVES | ORIGINATORS OF PREDATOR, Z-WEB AND AMBUSH ABRASIVES","u":"https://arcabrasives.com/"},{"t":"PRODUCT LINES","u":"https://arcabrasives.com/brands-products"},{"t":"ARC ABRASIVES | PRECISION PARTS & TOOLING","u":"https://pptholt.com/Search/Brand/ARC"},{"t":"ARC ABRASIVES | PACKER FASTENER","u":"https://www.packerfastener.com/catalog/parts/brand_grid.php?brand=ARC+Abrasives"},{"t":"ARC ABRASIVES - 71-31664K - ARC ABRASIVES QUICK-CHANGE SANDING DISC: TR, 3 IN DIA, CERAMIC, 50 GRIT, Y WT CLOTH, PREDATOR, 50 PK - AMAZON.COM","u":"https://www.amazon.com/ARC-Abrasives-71-31664K-Ceramic-Predator/dp/B01M0H6VVX"},{"t":"ARC ABRASIVES ARC","u":"https://www.turnersupply.com/Manufacturers/Arc-Abrasives/ARC"},{"t":"ARC ABRASIVES SANDING ABRASIVES","u":"https://www.grainger.com/category/abrasives/sanding-abrasives?brandName=ARC+ABRASIVES&filters=brandName"},{"t":"ARC ABRASIVES DISTRIBUTOR (89 ITEMS) | RAPTOR SUPPLIES WORLDWIDE","u":"https://www.raptorsupplies.com/b/arc-abrasives"},{"t":"ARC ABRASIVES","u":"https://business.walmart.com/browse/0?facet=brand:ARC+ABRASIVES"},{"t":"MARS SUPPLY | ARC ABRASIVES","u":"https://www.marssupply.com/Brands/ARC-ABRASIVES"},{"t":"WHOOPS, WE COULDN'T FIND THAT.","u":"https://www.grainger.com/category/brand/ARC+ABRASIVES"},{"t":"ARC ABRASIVES 1-1/2\" NON-WOVEN QUICK CHANGE DISC, TR ROLL-ON/OFF TYPE 3, MEDIUM, ALUMINUM OXIDE, 1 EA : AMAZON.CA: TOOLS & HOME IMPROVEMENT","u":"https://www.amazon.ca/ARC-ABRASIVES-Non-Woven-Change-Aluminum/dp/B07H9KSLWK"},{"t":"ARC ABRASIVES","u":"https://www.walmart.com/browse/arc-abrasives/YnJhbmQ6QVJDIEFCUkFTSVZFUwieie"},{"t":"ARC ABRASIVES 4-1/2\" FLAP DISC, TYPE 29, 5/8\"-11 MOUNTING HOLE, MEDIUM, 60 GRIT CERAMIC, 1 EA: AMAZON.COM: TOOLS & HOME IMPROVEMENT","u":"https://www.amazon.com/ARC-ABRASIVES-Mounting-Medium-Ceramic/dp/B07H9K7PL1"},{"t":"ARC ABRASIVES HOME IMPROVEMENT – WALMART.COM","u":"https://www.walmart.com/browse/home-improvement/arc-abrasives/1072864/YnJhbmQ6QVJDIEFCUkFTSVZFUwieie"},{"t":"ARC ABRASIVES 2\" NON-WOVEN QUICK CHANGE DISC, TS/TSM TURN-ON/OFF TYPE 2, COARSE, ALUMINUM OXIDE, 1 EA: AMAZON.COM: TOOLS & HOME IMPROVEMENT","u":"https://www.amazon.com/ARC-ABRASIVES-Non-Woven-Change-Aluminum/dp/B07H9HXPB1"},{"t":"ARC ABRASIVES PRODUCTS - RICHMOND SUPPLY COMPANY","u":"https://rsci.com/arc-abrasives/"},{"t":"ARC ABRASIVES FLAP DISC, 120 GRIT, FINE, 4-1/2 IN. DIA. : AMAZON.IN: INDUSTRIAL & SCIENTIFIC","u":"https://www.amazon.in/ARC-Abrasives-Flap-Disc-Grit/dp/B06W5QC83N"}]