[{"t":"B'N'M POLES - OVER 70 YEARS OF QUALITY AND PERFORMANCE","u":"https://www.bnmpoles.com/"},{"t":"B'N'M POLE COMPANY | WALMART CANADA","u":"https://www.walmart.ca/en/c/brand/b-n-m-pole-company"},{"t":"AMAZON.COM: FISHING RODS - B&M / FISHING RODS / FISHING RODS & ACCESSORIES: SPORTS & OUTDOORS","u":"https://www.amazon.com/Fishing-Rods-B-M-Accessories/s?keywords=Fishing+Rods&rh=n:3409871,p_89:B%2526M&c=ts&ts_id=3409871"},{"t":"B & M POLE ARCHIVES | SAFFORD TRADING COMPANY","u":"https://saffordtrading.com/brand/b-m-pole/"},{"t":"B'N'M POLE COMPANY @ AMAZON.COM:","u":"https://www.amazon.com/s?i=merchant-items&me=AGRU2CSVW8CFT"},{"t":"B&M-CANE-POLE PRODUCTS - PRESLEYS OUTDOORS","u":"https://www.presleysoutdoors.com/brands/B&M-CANE-POLE.html"},{"t":"B'N'M POLE COMPANY FISHING RODS IN FISHING - WALMART.COM","u":"https://www.walmart.com/browse/sports-outdoors/fishing-rods/b-n-m-pole-company/4125_546956_111667_7357023/YnJhbmQ6QiiduJ00gUG9sZSBDb21wYW55"},{"t":"AMAZON.COM: FISHING RODS - B / FISHING RODS / FISHING RODS & ACCESSORIES: SPORTS & OUTDOORS","u":"https://www.amazon.com/Fishing-Rods-B-Accessories/s?keywords=Fishing+Rods&rh=n:3409871,p_89:B&c=ts&ts_id=3409871"},{"t":"B'N'M POLE COMPANY 10' JOINTED BAMBOO FISHING ROD - WALMART.COM","u":"https://www.walmart.com/ip/B-n-M-Pole-Company-10-Jointed-Bamboo-Fishing-Rod/16326904"},{"t":"B’N’M POLE COMPANY - THE CRAPPIE BLOG","u":"https://thecrappieblog.com/bnm-pole-company/"},{"t":"B'N'M POLE COMPANY SALES - OVER 70 YEARS OF QUALITY AND PERFORMANCE","u":"https://www.polecompanys.com/"},{"t":"B'N'M FISHING RODS & POLES FOR SALE | EBAY","u":"https://www.ebay.com/b/BnM-Fishing-Rods-Poles/261028/bn_1943037"},{"t":"AMAZON.COM. SPEND LESS. SMILE MORE.","u":"https://www.amazon.com/"},{"t":"YOUR TACKLE BOX - B'N'M POLE COMPANY","u":"https://www.bnmpoles.com/cart"},{"t":"B&M | DISCOUNT RETAIL STORE | GARDEN, HOME, TOYS & MORE","u":"https://www.bmstores.co.uk/"},{"t":"BNM POLES","u":"https://www.walmart.com/c/brand/bnm-poles"}]