[{"t":"AMAZON.COM: C.R. GIBSON SIGNATURE","u":"https://www.amazon.com/stores/CRGibsonSignature/CRGibsonSignature/page/D373FC6E-B91D-4687-8DEA-AFE8DEC4439F"},{"t":"AMAZON.COM: C.R. GIBSON BABY","u":"https://www.amazon.com/stores/page/E5991ADE-4A4C-43FA-A465-2D3176EEE6EC"},{"t":"AMAZON.COM: C R GIBSON COMPANY: BOOKS","u":"https://www.amazon.com/Books-C-R-Gibson-Company/s?rh=n:283155,p_27:C%2BR%2BGibson%2BCompany"},{"t":"CR GIBSON - GIFTS & THINGS","u":"https://www.giftsandthingsholdregene.com/brand/CR-Gibson/"},{"t":"AMAZON.COM: C.R. GIBSON SIGNATURE: STATIONERY & JOURNALS","u":"https://www.amazon.com/stores/CRGibsonSignature/page/4C5AF4E8-0617-4113-8B6A-62838E51A490"},{"t":"AMAZON.COM: C.R. GIBSON SIGNATURE: JOURNALS","u":"https://www.amazon.com/stores/CRGibsonSignature/Journals_StationeryJournals/page/07B7489D-D32E-42D0-AFB4-5025C1CA857D"},{"t":"AMAZON.COM : C.R. GIBSON MJ5-4792 BROWN BONDED LEATHER NOTEBOOK WITH 240 RULED PAGES, 5\" W X 8.25\" H : HARDCOVER EXECUTIVE NOTEBOOKS : OFFICE PRODUCTS","u":"https://www.amazon.com/C-R-Gibson-Bonded-Leather-Journal/dp/B003M8GWI6"},{"t":"CR GIBSON - BI-MART","u":"https://www.bimart.com/brands/cr-gibson"},{"t":"AMAZON.COM: CR GIBSON COCKTAIL BEVERAGE PAPER NAPKINS, 40 CT, EEEEKKK! : HEALTH & HOUSEHOLD","u":"https://us.amazon.com/CR-Gibson-Cocktail-Beverage-Napkins/dp/B076HW8PW5"},{"t":"CR GIBSON BACKPACKS: COMPARE PRICES, REVIEWS & BUY ONLINE @ YAHOO SHOPPING","u":"https://shopping.yahoo.com/backpacks/cr-gibson--brand?limshp=1"},{"t":"AMAZON.COM: CR GIBSON: BOOKS","u":"https://www.amazon.com/Books-Cr-Gibson/s?rh=n:283155,p_27:Cr%2BGibson"},{"t":"SHOP OUR FULL COLLECTION OF CR GIBSON PRODUCTS AT BERINGS","u":"https://www.berings.com/brand/cr-gibson/"},{"t":"WHOLESALE CR GIBSON FOR YOUR STORE","u":"https://www.faire.com/discover/cr-gibson"},{"t":"SHOP AMAZON.COM | GIBSON STORE","u":"https://www.amazon.com/b?ie=UTF8&node=14485266011"},{"t":"C.R. GIBSON - POSHMARK","u":"https://poshmark.com/brand/c.r.%20gibson"},{"t":"WATCH FITLOSOPHY BRAND VIDEO ON AMAZON LIVE","u":"https://us.amazon.com/live/video/0672ad9fad5042a4bf9cd7e1fb09eb39?ref_=asvh_vdp"},{"t":"YAHOO","u":"https://shopping.yahoo.com/office/cr-gibson--brand"},{"t":"AMAZON.COM: MARKINGS BY C.R. GIBSON: OFFICE PRODUCTS","u":"https://www.amazon.com/Office-Products-Markings-C-R-Gibson/s?rh=n:1064954,p_15:Markings%2Bby%2BC.R.%2BGibson"},{"t":"C. R. GIBSON","u":"https://www.fatbraintoys.com/toys/brands/c_r_gibson/"}]