[{"t":"AMAZON BRAND USAGE GUIDELINES FOR 3-PARTY DISPLAY ADS | AMAZON ADS","u":"https://advertising.amazon.com/resources/ad-policy/brand-usage"},{"t":"ABOUT US | ABOUT AMAZON","u":"https://www.aboutamazon.com/about-us"},{"t":"WHAT ARE NEW-TO-BRAND METRICS, AND WHY SHOULD I USE THEM?","u":"https://advertising.amazon.com/solutions/products/sponsored-brands"},{"t":"AMAZON BRAND GUIDELINES: MUST-KNOW TO AVOID PENALIZATION","u":"https://sellerinteractive.com/blog/amazon-brand-guidelines-avoid-getting-penalized/"},{"t":"AMAZON BRAND REGISTRY | SELL ON AMAZON","u":"https://brandservices.amazon.com/"},{"t":"SPONSORED BRANDS – INCREASE BRAND AWARENESS | AMAZON ADS","u":"https://advertising.amazon.com/solutions/products/sponsored-brands"},{"t":"AMAZON","u":"https://sellercentral.amazon.com/seller-forums/discussions/t/cb0e14c72e806b357fc4099e5d3e53fd"},{"t":"70 AMAZON MUST-HAVES YOU NEED TO BUY IN 2025","u":"https://www.buzzfeed.com/malloryannp/things-you-can-get-on-amazon-that-you-should-just-own"},{"t":"A STEP-BY-STEP GUIDE FOR BUILDING YOUR BRAND ON AMAZON","u":"https://www.sellerapp.com/blog/build-brand-on-amazon/"},{"t":"REQUIREMENTS AND TIPS FOR ENROLLING A BRAND IN AMAZON BRAND REGISTRY ...","u":"https://brandservices.amazon.com/brandregistry/eligibility"},{"t":"AMAZON BRAND STORY: EVERYTHING YOU NEED TO KNOW - KENJI ROI","u":"https://kenjiroi.com/amazon-brand-story/"},{"t":"HOW AMAZON STEERS SHOPPERS TO ITS OWN PRODUCTS - THE NEW YORK TIMES","u":"https://www.nytimes.com/2018/06/23/business/amazon-the-brand-buster.html"},{"t":"AMAZON (COMPANY) - WIKIPEDIA","u":"https://en.wikipedia.org/wiki/Amazon_(company)"},{"t":"NECTAR BLOG | AMAZON GROWTH AND BRAND RECOGNITION: THREE FEATURES YOU CAN'T AFFORD TO IGNORE","u":"https://www.thinknectar.com/blog/amazon-growth-and-brand-recognition-three-features-you-cant-afford-to-ignore"},{"t":"AMAZON BRAND REGISTRY - COST, BENEFITS, & REQUIREMENTS - JUNGLE SCOUT","u":"https://www.junglescout.com/blog/amazon-brand-registry/"},{"t":"AMAZON BRAND USAGE GUIDELINES FOR PPC CAMPAIGNS","u":"https://myamazonguy.com/advertising/amazon-brand-usage-guidelines-for-ppc/"},{"t":"25 AMAZON MUST-HAVES THAT EVERYONE AND THEIR MOTHER IS WISHLISTING","u":"https://www.boredpanda.com/most-wished-for-favorites-on-amazon/"},{"t":"AMAZON BEST SELLERS: BEST OUR BRANDS","u":"https://www.amazon.com/Best-Sellers-Our-Brands/zgbs/private-brands"},{"t":"EVERYTHING YOU NEED TO KNOW ABOUT AMAZON BRAND STORY","u":"https://marketplaceamp.com/blog/everything-you-need-to-know-about-amazon-brand-story/"},{"t":"TOP BRANDS FROM AMAZON.COM'S BESTSELLER RANKINGS: MONTHLY REPORT","u":"https://metricscart.com/bestseller-reports/amazon-com/brands/"},{"t":"75 BEST-SELLING AMAZON PRODUCTS WORTH THE HYPE IN 2024 | GLAMOUR","u":"https://www.glamour.com/gallery/best-selling-amazon-products"}]