[{"t":"AMAZON BRAND REGISTRY | SELL ON AMAZON","u":"https://sell.amazon.com/brand-registry"},{"t":"AMAZON BRAND REGISTRY - AMAZON.COM","u":"https://brandregistry.amazon.com/"},{"t":"BRAND REGISTRY (TRADEMARK) VS AMAZON BRAND APPROVAL (NO TRADEMARK)","u":"https://www.reddit.com/r/FulfillmentByAmazon/comments/18l3lu5/brand_registry_trademark_vs_amazon_brand_approval/"},{"t":"REQUIREMENTS AND TIPS FOR ENROLLING A BRAND IN AMAZON BRAND REGISTRY - SELL ON AMAZON","u":"https://sell.amazon.com/blog/brand-registry-requirements"},{"t":"WHAT IS AMAZON BRAND REGISTRY? HOW DOES IT WORK? - SELL ON AMAZON","u":"https://sell.amazon.com/blog/what-is-amazon-brand-registry"},{"t":"HOW TO REGISTER YOUR BRAND IN AMAZON BRAND REGISTRY 2025","u":"https://m.youtube.com/watch?v=MYA3vHZjVGU"},{"t":"AMAZON BRAND REGISTRY - COST, BENEFITS, & REQUIREMENTS - JUNGLE SCOUT","u":"https://www.junglescout.com/blog/amazon-brand-registry/"},{"t":"R/FULFILLMENTBYAMAZON ON REDDIT: BRAND REGISTRY (TRADEMARK) VS AMAZON BRAND APPROVAL (NO TRADEMARK)","u":"https://www.reddit.com/r/FulfillmentByAmazon/comments/18l3lu5/brand_registry_trademark_vs_amazon_brand_approval/"},{"t":"AMAZON BRAND REGISTRY | PROTECT & PROMOTE YOUR BRAND","u":"https://myamazonguy.com/category/brand-registry/"},{"t":"AMAZON BRAND REGISTRY GUIDE | SARAS ANALYTICS","u":"https://www.sarasanalytics.com/blog/amazon-brand-registry"},{"t":"THE ULTIMATE AMAZON BRAND REGISTRY GUIDE","u":"https://www.ecomengine.com/amazon-brand-registry"},{"t":"ABOUT AMAZON BRAND REGISTRY","u":"https://sellercentral.amazon.com/help/hub/reference/external/200955930?locale=en-US"},{"t":"AMAZON BRAND REGISTRY","u":"https://www.tramatm.com/en/trademark-academy/article/amazon-brand-registry"},{"t":"HOW TO REGISTER YOUR BRAND ON AMAZON BRAND REGISTRY - MY REAL PROFIT – ANALYTICS ECOSYSTEM FOR AMAZON SELLERS","u":"https://myrealprofit.com/blog/how-to-register-your-brand-on-amazon-brand-registry/"},{"t":"AMAZON BRAND REGISTRY: BENEFITS & COMPLETE OVERVIEW FOR SELLERS IN 2024 | HELIUM 10","u":"https://www.helium10.com/blog/amazon-brand-registry/"},{"t":"5 AMAZON BRAND REGISTRY BENEFITS EVERY SELLER SHOULD KNOW - WEBFX","u":"https://www.webfx.com/blog/marketing/amazon-brand-registry-benefits/"},{"t":"AMAZON BRAND REGISTRY: HOW TO PROTECT YOUR BRAND ON AMAZON","u":"https://e-cabilly.com/resources/amazon-brand-registry/"},{"t":"AMAZON'S BRAND REGISTRY","u":"https://brandregistry.amazon.in/"},{"t":"MAXIMIZING SALES WITH AMAZON BRAND REGISTRY - YOUTUBE","u":"https://www.youtube.com/watch?v=iIBY6SAsXYE"},{"t":"LAUNCH YOUR BRAND WITH AMAZON.IN","u":"https://sell.amazon.in/brand-registry"},{"t":"AMAZON BRAND REGISTRY: STEP-BY-STEP GUIDE","u":"https://www.linkedin.com/pulse/amazon-brand-registry-step-by-step-guide-seller-assistant-app-ysqzf"}]