[{"t":"AMAZON.COM: UTAKU T-POST PULLER FENCE POST PULLER : AUTOMOTIVE","u":"https://www.amazon.com/UTAKU-T-Post-Puller-Fence-Post/dp/B0C1V8LG44"},{"t":"AMAZON.COM: UTAKU GALVANIZED RAISED GARDEN BEDS METAL PLANTER FOR FLOWERS HERBS VEGETABLES FRUITS (47\" X 27\") : PATIO, LAWN & GARDEN","u":"https://www.amazon.com/Galvanized-Raised-Planter-Flowers-Vegetables/dp/B09NVV37NS"},{"t":"PLAY UTAKU BY DARIO NUÑEZ, NILTÖX ON AMAZON MUSIC","u":"https://www.amazon.com/Utaku/dp/B086PJ2LJT"},{"t":"PLAY UTAKU BY DARIO NUNEZ & NILTOX ON AMAZON MUSIC","u":"https://www.amazon.com/Utaku/dp/B08R96FPCJ"},{"t":"UTAKU T-POST PULLER FENCE POST PULLER : AMAZON.CO.UK: AUTOMOTIVE","u":"https://www.amazon.co.uk/UTAKU-T-Post-Puller-Fence-Post/dp/B0C1V8LG44"},{"t":"UTAKU GARDEN HOSE REEL 65FT, RETRACTABLE MOUNT SWIVEL, 1/2\" WATER HOSE, 3/4\" NPT, GRAY : AMAZON.CO.UK: GARDEN","u":"https://www.amazon.co.uk/Garden-Retractable-Mount-Swivel-Water/dp/B09QHTD5CS"},{"t":"AMAZON - KOTO STUDIO","u":"https://koto.studio/work/amazon/"},{"t":"UTAKU 13\" DRAW KNIFE STRAIGHT DRAW SHAVE WOOD WOOKING : BUY ONLINE AT BEST PRICE IN KSA - SOUQ IS NOW AMAZON.SA: BEAUTY","u":"https://www.amazon.sa/-/en/UTAKU-Knife-Straight-Shave-Wooking/dp/B09MK2VYQ3"},{"t":"AMAZON.COM: : ALL DEPARTMENTS","u":"https://www.amazon.com/b?ie=UTF8&node=17602470011"},{"t":"UTA SHOP @ AMAZON.COM:","u":"https://www.amazon.com/s?i=merchant-items&me=A1XSFJACUEK983"},{"t":"AMAZON.COM: UNI","u":"https://www.amazon.com/stores/page/A18BBD7E-D912-4E95-ACF3-21BCD73ABF83"},{"t":"ABOUT US | ABOUT AMAZON","u":"https://www.aboutamazon.com/about-us"},{"t":"AMAZON.COM. SPEND LESS. SMILE MORE.","u":"https://www.amazon.com/"},{"t":"AMAZON (COMPANY) - WIKIPEDIA","u":"https://en.wikipedia.org/wiki/Amazon_(company)"},{"t":"ABOUT US – UTTU","u":"https://uttu.cc/pages/about-us"},{"t":"REPRODUCIR UTAKU DE DARIO NUÑEZ, NILTÖX EN AMAZON MUSIC","u":"https://www.amazon.com/-/es/NILT%C3%96X-Dario-Nu%C3%B1ez/dp/B086P7JL2T"},{"t":"AMAZON.ES","u":"https://www.amazon.es/Utaku/dp/B086Q2PXK7"},{"t":"UTAKU - AMAZON","u":"https://www.amazon.fr/Utaku/dp/B086Q5Y9YK"},{"t":"AMAZON.DE","u":"https://www.amazon.de/Utaku/dp/B08R96MC3B"},{"t":"UTAKU T-PFOSTENABZIEHER ZAUNPFOSTENABZIEHER : AMAZON.DE: BAUMARKT","u":"https://www.amazon.de/UTAKU-PP-002-T-Pfostenabzieher-Zaunpfostenabzieher/dp/B0C1V8LG44"}]