[{"t":"AMAZON.IN: AMAZONBASICS","u":"https://www.amazon.in/b?ie=UTF8&node=6637738031"},{"t":"LIST OF AMAZON BRANDS - WIKIPEDIA","u":"https://en.wikipedia.org/wiki/List_of_Amazon_brands"},{"t":"AMAZON.COM: AMAZON BASICS 3 SHELVES UTILITY CART WITH 400 LBS LOADING CAPACITY, SMOOTH MOVE, GRAY (PREVIOUSLY AMAZONCOMMERCIAL BRAND) : OFFICE PRODUCTS","u":"https://www.amazon.com/AmazonCommercial-Shelves-Utility-Loading-Capacity/dp/B07TM5Q939"},{"t":"AMAZON.COM: AMAZON BASICS","u":"https://www.amazon.com/stores/AmazonBasics/AmazonBasics/page/947C6949-CF8E-4BD3-914A-B411DD3E4433"},{"t":"WHAT IS AMAZON BASICS? 2024 GUIDE FOR SELLERS - JUNGLE SCOUT","u":"https://www.junglescout.com/blog/amazon-basics/"},{"t":"AMAZON.COM: : ALL DEPARTMENTS","u":"https://www.amazon.com/b?ie=UTF8&node=17602470011"},{"t":"WHAT IS AMAZONBASICS? | TINUITI","u":"https://tinuiti.com/blog/amazon/amazon-basics/"},{"t":"AMAZON.COM: AMAZON BASICS: ELECTRONICS","u":"https://www.amazon.com/stores/AmazonBasics/page/3057D85A-05B6-4C31-9541-BAA49DF37652"},{"t":"AMAZON.COM: AMAZON BASICS 3-TIER METAL ROLLING UTILITY OR KITCHEN CART - WHITE : OFFICE PRODUCTS","u":"https://www.amazon.com/AmazonBasics-3-Tier-Rolling-Utility-Kitchen/dp/B07TY1RFH5"},{"t":"WHAT IS AMAZONBASICS AND WHAT YOU SHOULD KNOW AS AN AMAZON SELLER?","u":"https://www.zonguru.com/blog/what-is-amazon-basics"},{"t":"THREECOLTS: WHAT AMAZON SELLERS NEED TO KNOW ABOUT AMAZON BASICS IN 2024","u":"https://www.threecolts.com/blog-articles/amazon-basics"},{"t":"AMAZON BASICS FOLDING UTILITY KNIFE, LIGHTWEIGHT ALUMINUM BODY, RED - AMAZON.COM","u":"https://www.amazon.com/AmazonBasics-Folding-Utility-Knife-Lightweight/dp/B07TBNH4ZT"},{"t":"WATCH A LIGHTWEIGHT AND VERSATILE UTILITY KNIFE FROM AMAZON BASICS ON AMAZON LIVE","u":"https://www.amazon.com/live/video/0588ce5b9a0f4a60beb5eedccd8ba962?ref_=dp_vse_rvc_5"},{"t":"COMPARE GOODTHREADS, AMAZON AWARE, AMAZON ESSENTIALS AND MORE AMAZON PRIME BRANDS FOR MEN (2025)","u":"https://www.modernfellows.com/here-are-the-differences-between-amazon-essentials-goodthreads-buttoned-down-and-other-amazon-prime-brands/"},{"t":"AMAZON.COM: AMAZONBASICS","u":"https://www.amazon.com/AmazonBasics/s?k=AmazonBasics"},{"t":"AMAZON.CA: AMAZON BASICS - UTILITY CARTS / HOME OFFICE CARTS: HOME & KITCHEN","u":"https://www.amazon.ca/Utility-Carts-Amazon-Basics-Home-Office/s?rh=n:7239744011,p_89:Amazon+Basics"},{"t":"AMAZONBASICS: A GUIDE TO THE GOOD, THE BAD, AND THE SPONTANEOUSLY COMBUSTIBLE","u":"https://www.popsci.com/story/diy/amazonbasics-guide-best-products/"},{"t":"EVERYTHING YOU NEED TO KNOW ABOUT AMAZON PRIVATE LABELS","u":"https://www.scrapehero.com/everything-you-need-to-know-about-amazon-private-labels/"},{"t":"AMAZON BRAND - SYMBOL WOMEN'S REGULAR WORK UTILITY PANTS : AMAZON.IN: FASHION","u":"https://www.amazon.in/Amazon-Brand-Symbol-Regular-Utility/dp/B0C4CZRMD4"},{"t":"16 AMAZON BASICS PRODUCTS WORTH BUYING OVER THEIR NAME-BRAND COUNTERPARTS","u":"https://www.mentalfloss.com/smart-shopping/best-amazonbasics-products"}]