[{"t":"AMAZON.COM: ZEWEIERSLIME","u":"https://www.amazon.com/stores/ZeweierSlime/page/DDC558A7-44F0-4085-8B99-B2F140C3A3BE"},{"t":"Amazon Brand Registry | Sell on Amazon","u":"https://sell.amazon.com/brand-registry"},{"t":"Who can create a Brand Store?","u":"https://advertising.amazon.com/solutions/products/stores"},{"t":"Amazon (company) - Wikipedia","u":"https://en.wikipedia.org/wiki/Amazon_(company)"},{"t":"Amazon.in: : All Categories","u":"https://www.amazon.in/b?ie=UTF8&node=15390370031"},{"t":"Our Brands","u":"https://www.amazon.com/fmc/m/20190596?almBrandId=QW1hem9uIEZyZXNo"},{"t":"Amazon - Koto Studio","u":"https://koto.studio/work/amazon/"},{"t":"List of Amazon brands - Wikipedia","u":"https://en.wikipedia.org/wiki/List_of_Amazon_brands"},{"t":"Brand Stores: Create a brand page on Amazon for free | Amazon Ads","u":"https://advertising.amazon.com/solutions/products/stores"},{"t":"Amazon.com: : All Departments","u":"https://www.amazon.com/b?ie=UTF8&node=17602470011"},{"t":"Amazon.com: Our Brands: Clothing, Shoes & Jewelry","u":"https://www.amazon.com/b?ie=UTF8&node=16334314011"},{"t":"Amazon Best Sellers: Best Our Brands","u":"https://www.amazon.com/Best-Sellers-Our-Brands/zgbs/private-brands"},{"t":"About Us | About Amazon","u":"https://www.aboutamazon.com/about-us"},{"t":"Sponsored Brands – Increase brand awareness | Amazon Ads","u":"https://advertising.amazon.com/solutions/products/sponsored-brands"},{"t":"Posts: Image and Video led browsing on Amazon | Amazon Ads","u":"https://advertising.amazon.com/solutions/products/posts"},{"t":"Amazon.com: Deals on Amazon Brands: Clothing, Shoes & Jewelry","u":"https://www.amazon.com/b?ie=UTF8&node=23728606011"},{"t":"Amazon.com. Spend less. Smile more.","u":"https://www.amazon.com/"},{"t":"Amazon.com: Best of Premium Brands","u":"https://www.amazon.com/b?ie=UTF8&node=24001920011"},{"t":"Amazon's new shopping feature lets you search for products even if they're not sold on Amazon","u":"https://www.aboutamazon.com/news/retail/search-products-amazon-shopping-feature"},{"t":"Amazon.com: Amazon Essentials","u":"https://www.amazon.com/stores/AmazonEssentials/page/F8FB6F3C-F896-455C-BC52-7879F4CEF0CF"}]